MANIFEST.in
README.txt
requirements.txt
setup.py
semantic3/__init__.py
semantic3/dates.py
semantic3/numbers.py
semantic3/solver.py
semantic3/units.py
semantic3.egg-info/PKG-INFO
semantic3.egg-info/SOURCES.txt
semantic3.egg-info/dependency_links.txt
semantic3.egg-info/requires.txt
semantic3.egg-info/top_level.txt
semantic3/test/__init__.py
semantic3/test/testConversion.py
semantic3/test/testDates.py
semantic3/test/testMath.py
semantic3/test/testNumbers.py